{
  "name": "中立守護者の道",
  "description": [
    "バランスのとれた道を歩み、均衡の守護者になりましょう！",
    "すべての力の間のバランスを維持し、自然の秩序を守りましょう。",
    "",
    "⚖️ 守護者の利益：",
    "• バランス操作能力",
    "• すべての元素との調和",
    "• 平和的解決技術",
    "• 自然秩序保護",
    "• 普遍的な尊敬と信頼"
  ],
  "objectives": {
    "seek_balance": "バランスの概念を理解",
    "meditate_elements": "四つの元素と瞑想",
    "resolve_conflicts": "10の紛争を平和的に解決",
    "protect_neutrality": "中立領土を保護",
    "study_philosophy": "古代バランス哲学を研究",
    "help_both_sides": "善と悪の両方を支援",
    "restore_harmony": "堕落した土地に調和を回復",
    "unite_factions": "対立する派閥を統合",
    "balance_ritual": "偉大なバランス儀式を行う",
    "speak_all_languages": "すべての存在とコミュニケーションする方法を学習",
    "judge_fairly": "複雑な道徳的状況を公正に判断",
    "maintain_peace": "大きな紛争中に平和を維持",
    "guardian_trials": "守護者の試練を完了",
    "receive_blessing": "すべての力から祝福を受ける",
    "become_eternal_guardian": "永遠のバランス守護者になる"
  },
  "npcs": {
    "balance_keeper": "バランスの番人",
    "neutral_sage": "中立の賢者",
    "harmony_spirit": "調和の精霊"
  },
  "dialogs": {
    "start": "バランスの道は善と悪を超えた知恵が必要です。理解していますか？",
    "learning": "真の力は側を選ぶことではなく、すべての視点を理解することにあります。",
    "conflict": "すべての紛争には両面があります。守護者は両方を等しい明晰さで見ます。",
    "harmony": "あなたは他の者が戦争をもたらす場所に平和をもたらします。これがバランスの道です。",
    "trials": "試練はあなたの力ではなく、知恵と思いやりを試します。",
    "complete": "あなたは今永遠の守護者です。バランスがあなたのすべての歩みを導きますように。"
  }
}