{
  "name": "神秘の洞窟",
  "description": [
    "最近発見された洞窟システムから",
    "奇妙な音と光る光が漏れ出ています。",
    "",
    "未知の深淵を勇敢に探検して、",
    "その中の神秘的な現象の源を解明してください。"
  ],
  "objectives": {
    "enter_cave_system": "神秘の洞窟システムに入る",
    "investigate_glowing_crystals": "光る水晶の形成物を調査する",
    "defeat_cave_dwellers": "影の洞窟住人を15体倒す",
    "find_underground_lake": "地下湖を発見する",
    "solve_crystal_puzzle": "古代水晶パズルを解く",
    "claim_cave_treasure": "隠された洞窟の宝を手に入れる"
  },
  "npcs": {
    "cave_explorer": "経験豊富な洞窟探検家",
    "crystal_guardian": "水晶の守護者",
    "echo_spirit": "深淵の反響精霊"
  },
  "dialogs": {
    "start1": "この洞窟は...私が今まで探検したどこよりも異なります。",
    "start2": "水晶が超自然的なエネルギーで脈動しています。",
    "start3": "この深部に古代の何かが眠っています。",
    "progress1": "影がここでは自分で動いているようです。",
    "progress2": "聞いてください...闇の中のささやきが聞こえますか？",
    "complete1": "洞窟の秘密が明かされました！",
    "complete2": "あなたは地下の永遠の闇に光をもたらしました。"
  }
}