{
  "objectives": {
    "solstice.beach_contest": "Beach Contest",
    "solstice.blaze_powder_collect": "Blaze Powder Collect",
    "solstice.build_altar": "Build Altar",
    "solstice.cake_deliver": "Cake Deliver",
    "solstice.dandelion_collect": "Dandelion Collect",
    "solstice.defeat_blazes": "Defeat Blazes",
    "solstice.desert_temple": "Desert Temple",
    "solstice.festival_complete": "Festival Complete",
    "solstice.festival_coordinator": "Festival Coordinator",
    "solstice.festival_grounds": "Festival Grounds",
    "solstice.firework_rocket_collect": "Firework Rocket Collect",
    "solstice.firework_rocket_craft": "Firework Rocket Craft",
    "solstice.flower_garden": "Flower Garden",
    "solstice.gold_ingot_collect": "Gold Ingot Collect",
    "solstice.golden_apple_collect": "Golden Apple Collect",
    "solstice.golden_apple_craft": "Golden Apple Craft",
    "solstice.guardian_challenge": "Guardian Challenge",
    "solstice.gunpowder_collect": "Gunpowder Collect",
    "solstice.heat_endurance": "Heat Endurance",
    "solstice.ice_collect": "Ice Collect",
    "solstice.melon_craft": "Melon Craft",
    "solstice.melon_slice_collect": "Melon Slice Collect",
    "solstice.orange_tulip_collect": "Orange Tulip Collect",
    "solstice.poppy_deliver": "Poppy Deliver",
    "solstice.potion_craft": "Potion Craft",
    "solstice.prismarine_shard_collect": "Prismarine Shard Collect",
    "solstice.red_dye_collect": "Red Dye Collect",
    "solstice.sun_offering": "Sun Offering",
    "solstice.sun_priest": "Sun Priest",
    "solstice.sunflower_collect": "Sunflower Collect",
    "solstice.swimming_race": "Swimming Race"
  }
}